billingoclient/__init__.py
billingoclient/billingo_client.py
billingoclient/jwt_header.py
billingoclient/dto/__init__.py
billingoclient/dto/invoice.py
billingoclient-0.0.2.dist-info/METADATA
billingoclient-0.0.2.dist-info/WHEEL
billingoclient-0.0.2.dist-info/top_level.txt
billingoclient-0.0.2.dist-info/RECORD
