Metadata-Version: 2.1
Name: billingoclient
Version: 0.0.2
Summary: Python package to access billingo rest api
Home-page: UNKNOWN
Author: Mocsar Kalman
Author-email: mocsar@yusp.com
License: UNKNOWN
Platform: UNKNOWN
Classifier: Programming Language :: Python :: 3
Classifier: Operating System :: OS Independent
Requires-Python: >=3.7
Requires-Dist: requests (>=2.23.0)
Requires-Dist: PyJWT (>=1.7.1)
